AUTHORS
LICENSE
MANIFEST.in
README
setup.cfg
setup.py
sonar_rules_extractor/__init__.py
sonar_rules_extractor/cmdline.py
sonar_rules_extractor/extractor.py
sonar_rules_extractor/rule.py
sonar_rules_extractor.egg-info/PKG-INFO
sonar_rules_extractor.egg-info/SOURCES.txt
sonar_rules_extractor.egg-info/dependency_links.txt
sonar_rules_extractor.egg-info/entry_points.txt
sonar_rules_extractor.egg-info/not-zip-safe
sonar_rules_extractor.egg-info/top_level.txt
sonar_rules_extractor/tools/__init__.py
sonar_rules_extractor/tools/cppcheck.py
sonar_rules_extractor/tools/cpptest.py
sonar_rules_extractor/tools/gnatcheck.py
sonar_rules_extractor/tools/klocwork.py
sonar_rules_extractor/tools/logiscope.py
sonar_rules_extractor/tools/prqa.py
sonar_rules_extractor/tools/pylint.py