Metadata-Version: 1.1
Name: sonar-rules-extractor
Version: 1.1
Summary: Coding rules extractor into the Sonar format.
Home-page: http://pypi.python.org/pypi/sonar-rules-extractor
Author: Robin Jarry
Author-email: robin.jarry@external.thalesgroup.com
License: MIT
Platform: any
Classifier: Development Status :: 4 - Beta
Classifier: Environment :: Console
Classifier: Intended Audience :: Developers
Classifier: License :: OSI Approved :: MIT License
Classifier: Operating System :: OS Independent
Classifier: Programming Language :: Python
Classifier: Programming Language :: Python :: 2
Classifier: Topic :: Documentation
Classifier: Topic :: Text Processing
Classifier: Topic :: Utilities
Provides: sonar_rules_extractor
